{
    "schemes": [
        "http",
        "https"
    ],
    "swagger": "2.0",
    "info": {
        "description": "OAuth 2.0 authorization and user authentication service for the library management system.\nThis service uses opaque bearer tokens, Authorization Code with PKCE, and HttpOnly session cookies.",
        "title": "Library Management Auth API",
        "contact": {},
        "version": "1.0"
    },
    "basePath": "/",
    "paths": {
        "/.well-known/oauth-authorization-server": {
            "get": {
                "description": "Returns RFC 8414 discovery metadata for this OAuth server.",
                "produces": [
                    "application/json"
                ],
                "tags": [
                    "OAuth"
                ],
                "summary": "Get authorization server metadata",
                "responses": {
                    "200": {
                        "description": "Authorization server metadata",
                        "schema": {
                            "$ref": "#/definitions/response.OAuthMetadata"
                        }
                    }
                }
            }
        },
        "/api/v1/auth/login": {
            "post": {
                "description": "Authenticates a user and sets an HttpOnly session cookie. HTML form requests are also accepted. A valid returnTo redirects with 303.",
                "consumes": [
                    "application/json"
                ],
                "produces": [
                    "application/json"
                ],
                "tags": [
                    "Authentication"
                ],
                "summary": "Log in",
                "parameters": [
                    {
                        "description": "Login details",
                        "name": "request",
                        "in": "body",
                        "required": true,
                        "schema": {
                            "$ref": "#/definitions/request.Login"
                        }
                    }
                ],
                "responses": {
                    "200": {
                        "description": "Authenticated user",
                        "schema": {
                            "$ref": "#/definitions/response.UserSuccess"
                        }
                    },
                    "303": {
                        "description": "Redirect to authorization flow",
                        "schema": {
                            "type": "string"
                        }
                    },
                    "401": {
                        "description": "Invalid credentials",
                        "schema": {
                            "$ref": "#/definitions/response.ErrorResponse"
                        }
                    },
                    "403": {
                        "description": "Untrusted request origin",
                        "schema": {
                            "$ref": "#/definitions/response.ErrorResponse"
                        }
                    },
                    "422": {
                        "description": "Invalid login data or return URL",
                        "schema": {
                            "$ref": "#/definitions/response.ErrorResponse"
                        }
                    },
                    "429": {
                        "description": "Rate limit exceeded",
                        "schema": {
                            "$ref": "#/definitions/response.ErrorResponse"
                        }
                    },
                    "500": {
                        "description": "Internal error",
                        "schema": {
                            "$ref": "#/definitions/response.ErrorResponse"
                        }
                    }
                }
            }
        },
        "/api/v1/auth/logout": {
            "post": {
                "description": "Revokes the session identified by the lms_session cookie and clears that cookie.",
                "tags": [
                    "Authentication"
                ],
                "summary": "Log out",
                "parameters": [
                    {
                        "type": "string",
                        "description": "Session cookie: lms_session=token",
                        "name": "Cookie",
                        "in": "header",
                        "required": true
                    }
                ],
                "responses": {
                    "204": {
                        "description": "Session revoked"
                    },
                    "401": {
                        "description": "Invalid session",
                        "schema": {
                            "$ref": "#/definitions/response.ErrorResponse"
                        }
                    },
                    "403": {
                        "description": "Untrusted request origin",
                        "schema": {
                            "$ref": "#/definitions/response.ErrorResponse"
                        }
                    },
                    "500": {
                        "description": "Internal error",
                        "schema": {
                            "$ref": "#/definitions/response.ErrorResponse"
                        }
                    }
                }
            }
        },
        "/api/v1/auth/me": {
            "get": {
                "description": "Returns the user identified by the lms_session cookie.",
                "produces": [
                    "application/json"
                ],
                "tags": [
                    "Authentication"
                ],
                "summary": "Get current user",
                "parameters": [
                    {
                        "type": "string",
                        "description": "Session cookie: lms_session=token",
                        "name": "Cookie",
                        "in": "header",
                        "required": true
                    }
                ],
                "responses": {
                    "200": {
                        "description": "Current user",
                        "schema": {
                            "$ref": "#/definitions/response.UserSuccess"
                        }
                    },
                    "401": {
                        "description": "Invalid session",
                        "schema": {
                            "$ref": "#/definitions/response.ErrorResponse"
                        }
                    },
                    "500": {
                        "description": "Internal error",
                        "schema": {
                            "$ref": "#/definitions/response.ErrorResponse"
                        }
                    }
                }
            }
        },
        "/api/v1/auth/register": {
            "post": {
                "description": "Creates a user account. Requests from browsers must use the configured trusted Origin.",
                "consumes": [
                    "application/json"
                ],
                "produces": [
                    "application/json"
                ],
                "tags": [
                    "Authentication"
                ],
                "summary": "Register user",
                "parameters": [
                    {
                        "description": "Registration details",
                        "name": "request",
                        "in": "body",
                        "required": true,
                        "schema": {
                            "$ref": "#/definitions/request.Register"
                        }
                    }
                ],
                "responses": {
                    "201": {
                        "description": "User created",
                        "schema": {
                            "$ref": "#/definitions/response.UserSuccess"
                        }
                    },
                    "403": {
                        "description": "Untrusted request origin",
                        "schema": {
                            "$ref": "#/definitions/response.ErrorResponse"
                        }
                    },
                    "409": {
                        "description": "Email already registered",
                        "schema": {
                            "$ref": "#/definitions/response.ErrorResponse"
                        }
                    },
                    "422": {
                        "description": "Invalid registration data",
                        "schema": {
                            "$ref": "#/definitions/response.ErrorResponse"
                        }
                    },
                    "429": {
                        "description": "Rate limit exceeded",
                        "schema": {
                            "$ref": "#/definitions/response.ErrorResponse"
                        }
                    },
                    "500": {
                        "description": "Internal error",
                        "schema": {
                            "$ref": "#/definitions/response.ErrorResponse"
                        }
                    }
                }
            }
        },
        "/api/v1/oauth/userinfo": {
            "get": {
                "security": [
                    {
                        "BearerAuth": []
                    }
                ],
                "produces": [
                    "application/json"
                ],
                "tags": [
                    "OAuth"
                ],
                "summary": "Get token user",
                "responses": {
                    "200": {
                        "description": "Token user",
                        "schema": {
                            "$ref": "#/definitions/response.UserSuccess"
                        }
                    },
                    "401": {
                        "description": "Invalid or expired access token",
                        "schema": {
                            "$ref": "#/definitions/response.ErrorResponse"
                        }
                    },
                    "404": {
                        "description": "User not found",
                        "schema": {
                            "$ref": "#/definitions/response.ErrorResponse"
                        }
                    },
                    "500": {
                        "description": "Internal error",
                        "schema": {
                            "$ref": "#/definitions/response.ErrorResponse"
                        }
                    }
                }
            }
        },
        "/health/liveness": {
            "get": {
                "produces": [
                    "application/json"
                ],
                "tags": [
                    "Health"
                ],
                "summary": "Check liveness",
                "responses": {
                    "200": {
                        "description": "Process is live",
                        "schema": {
                            "$ref": "#/definitions/response.Health"
                        }
                    }
                }
            }
        },
        "/health/readiness": {
            "get": {
                "produces": [
                    "application/json"
                ],
                "tags": [
                    "Health"
                ],
                "summary": "Check readiness",
                "responses": {
                    "200": {
                        "description": "Service is ready",
                        "schema": {
                            "$ref": "#/definitions/response.Health"
                        }
                    },
                    "503": {
                        "description": "A required dependency is unavailable",
                        "schema": {
                            "$ref": "#/definitions/response.Health"
                        }
                    }
                }
            }
        },
        "/oauth/authorize": {
            "get": {
                "description": "Validates the client, redirect URI, state, and S256 PKCE challenge. Redirects unauthenticated users to login.",
                "tags": [
                    "OAuth"
                ],
                "summary": "Authorize OAuth client",
                "parameters": [
                    {
                        "enum": [
                            "code"
                        ],
                        "type": "string",
                        "description": "OAuth response type",
                        "name": "response_type",
                        "in": "query",
                        "required": true
                    },
                    {
                        "type": "string",
                        "description": "OAuth client ID",
                        "name": "client_id",
                        "in": "query",
                        "required": true
                    },
                    {
                        "type": "string",
                        "description": "Exact registered callback URL",
                        "name": "redirect_uri",
                        "in": "query",
                        "required": true
                    },
                    {
                        "type": "string",
                        "description": "Space-delimited scopes",
                        "name": "scope",
                        "in": "query",
                        "required": true
                    },
                    {
                        "type": "string",
                        "description": "CSRF correlation value",
                        "name": "state",
                        "in": "query",
                        "required": true
                    },
                    {
                        "type": "string",
                        "description": "Base64url-encoded SHA-256 PKCE challenge",
                        "name": "code_challenge",
                        "in": "query",
                        "required": true
                    },
                    {
                        "enum": [
                            "S256"
                        ],
                        "type": "string",
                        "description": "PKCE method",
                        "name": "code_challenge_method",
                        "in": "query",
                        "required": true
                    }
                ],
                "responses": {
                    "302": {
                        "description": "Redirect to login or callback with authorization code",
                        "schema": {
                            "type": "string"
                        }
                    },
                    "400": {
                        "description": "Invalid authorization request",
                        "schema": {
                            "$ref": "#/definitions/oauth.OAuthErrorResponse"
                        }
                    }
                }
            }
        },
        "/oauth/introspect": {
            "post": {
                "security": [
                    {
                        "BasicAuth": []
                    }
                ],
                "description": "RFC 7662 endpoint restricted to provisioned resource-server clients using HTTP Basic.",
                "consumes": [
                    "application/x-www-form-urlencoded"
                ],
                "produces": [
                    "application/json"
                ],
                "tags": [
                    "OAuth"
                ],
                "summary": "Introspect access token",
                "parameters": [
                    {
                        "type": "string",
                        "description": "Opaque access token",
                        "name": "token",
                        "in": "formData",
                        "required": true
                    },
                    {
                        "enum": [
                            "access_token"
                        ],
                        "type": "string",
                        "description": "Token type hint",
                        "name": "token_type_hint",
                        "in": "formData"
                    }
                ],
                "responses": {
                    "200": {
                        "description": "Token state; inactive tokens include only active=false",
                        "schema": {
                            "$ref": "#/definitions/oauth.OAuthIntrospectionResponse"
                        }
                    },
                    "400": {
                        "description": "Token missing or request invalid",
                        "schema": {
                            "$ref": "#/definitions/oauth.OAuthErrorResponse"
                        }
                    },
                    "401": {
                        "description": "Client authentication or authorization failed",
                        "schema": {
                            "$ref": "#/definitions/oauth.OAuthErrorResponse"
                        }
                    },
                    "500": {
                        "description": "Token state could not be determined",
                        "schema": {
                            "$ref": "#/definitions/oauth.OAuthErrorResponse"
                        }
                    }
                }
            }
        },
        "/oauth/token": {
            "post": {
                "security": [
                    {
                        "BasicAuth": []
                    }
                ],
                "description": "Supports authorization_code, refresh_token, and provisioned client_credentials clients. Client authentication uses HTTP Basic.",
                "consumes": [
                    "application/x-www-form-urlencoded"
                ],
                "produces": [
                    "application/json"
                ],
                "tags": [
                    "OAuth"
                ],
                "summary": "Issue OAuth token",
                "parameters": [
                    {
                        "enum": [
                            "authorization_code",
                            "refresh_token",
                            "client_credentials"
                        ],
                        "type": "string",
                        "description": "OAuth grant type",
                        "name": "grant_type",
                        "in": "formData",
                        "required": true
                    },
                    {
                        "type": "string",
                        "description": "Authorization code; required for authorization_code",
                        "name": "code",
                        "in": "formData"
                    },
                    {
                        "type": "string",
                        "description": "Exact callback URL; required for authorization_code",
                        "name": "redirect_uri",
                        "in": "formData"
                    },
                    {
                        "type": "string",
                        "description": "PKCE verifier; required for authorization_code",
                        "name": "code_verifier",
                        "in": "formData"
                    },
                    {
                        "type": "string",
                        "description": "Refresh token; required for refresh_token",
                        "name": "refresh_token",
                        "in": "formData"
                    },
                    {
                        "type": "string",
                        "description": "Space-delimited requested scopes",
                        "name": "scope",
                        "in": "formData"
                    }
                ],
                "responses": {
                    "200": {
                        "description": "Token issued",
                        "schema": {
                            "$ref": "#/definitions/oauth.OAuthTokenResponse"
                        }
                    },
                    "400": {
                        "description": "Invalid request or grant",
                        "schema": {
                            "$ref": "#/definitions/oauth.OAuthErrorResponse"
                        }
                    },
                    "401": {
                        "description": "Client authentication failed",
                        "schema": {
                            "$ref": "#/definitions/oauth.OAuthErrorResponse"
                        }
                    },
                    "429": {
                        "description": "Rate limit exceeded",
                        "schema": {
                            "$ref": "#/definitions/oauth.APIErrorResponse"
                        }
                    }
                }
            }
        }
    },
    "definitions": {
        "oauth.APIErrorResponse": {
            "type": "object",
            "properties": {
                "code": {
                    "type": "string",
                    "example": "LMS-429001"
                },
                "message": {
                    "type": "string",
                    "example": "too many authentication attempts"
                }
            }
        },
        "oauth.OAuthErrorResponse": {
            "type": "object",
            "properties": {
                "error": {
                    "type": "string",
                    "example": "invalid_request"
                },
                "error_description": {
                    "type": "string",
                    "example": "the request is invalid"
                }
            }
        },
        "oauth.OAuthIntrospectionResponse": {
            "type": "object",
            "properties": {
                "active": {
                    "type": "boolean",
                    "example": true
                },
                "client_id": {
                    "type": "string",
                    "example": "member-nextjs-web"
                },
                "exp": {
                    "type": "integer",
                    "example": 1784448900
                },
                "iat": {
                    "type": "integer",
                    "example": 1784448000
                },
                "iss": {
                    "type": "string",
                    "example": "http://localhost:8081"
                },
                "scope": {
                    "type": "string",
                    "example": "library:read"
                },
                "sub": {
                    "type": "string",
                    "example": "f81d4fae-7dec-11d0-a765-00a0c91e6bf6"
                },
                "token_type": {
                    "type": "string",
                    "example": "Bearer"
                }
            }
        },
        "oauth.OAuthTokenResponse": {
            "type": "object",
            "properties": {
                "access_token": {
                    "type": "string",
                    "example": "opaque-access-token"
                },
                "expires_in": {
                    "type": "integer",
                    "example": 900
                },
                "refresh_token": {
                    "type": "string",
                    "example": "opaque-refresh-token"
                },
                "scope": {
                    "type": "string",
                    "example": "library:read library:write"
                },
                "token_type": {
                    "type": "string",
                    "example": "Bearer"
                }
            }
        },
        "request.Login": {
            "type": "object",
            "required": [
                "email",
                "password"
            ],
            "properties": {
                "email": {
                    "type": "string",
                    "maxLength": 254,
                    "example": "ada@example.com"
                },
                "password": {
                    "type": "string",
                    "maxLength": 72,
                    "example": "correct horse battery staple"
                },
                "returnTo": {
                    "type": "string",
                    "example": "http://localhost:8081/oauth/authorize"
                }
            }
        },
        "request.Register": {
            "type": "object",
            "required": [
                "email",
                "name",
                "password"
            ],
            "properties": {
                "email": {
                    "type": "string",
                    "maxLength": 254,
                    "example": "ada@example.com"
                },
                "name": {
                    "type": "string",
                    "maxLength": 100,
                    "minLength": 2,
                    "example": "Ada Lovelace"
                },
                "password": {
                    "type": "string",
                    "maxLength": 72,
                    "minLength": 12,
                    "example": "correct horse battery staple"
                }
            }
        },
        "response.ErrorResponse": {
            "type": "object",
            "properties": {
                "code": {
                    "type": "string",
                    "example": "LMS-422001"
                },
                "data": {},
                "message": {
                    "type": "string",
                    "example": "invalid request data"
                }
            }
        },
        "response.Health": {
            "type": "object",
            "properties": {
                "status": {
                    "type": "string",
                    "example": "ok"
                }
            }
        },
        "response.OAuthMetadata": {
            "type": "object",
            "properties": {
                "authorization_endpoint": {
                    "type": "string",
                    "example": "http://localhost:8081/oauth/authorize"
                },
                "code_challenge_methods_supported": {
                    "type": "array",
                    "items": {
                        "type": "string"
                    },
                    "example": [
                        "S256"
                    ]
                },
                "grant_types_supported": {
                    "type": "array",
                    "items": {
                        "type": "string"
                    },
                    "example": [
                        "authorization_code",
                        "refresh_token",
                        "client_credentials"
                    ]
                },
                "introspection_endpoint": {
                    "type": "string",
                    "example": "http://localhost:8081/oauth/introspect"
                },
                "issuer": {
                    "type": "string",
                    "example": "http://localhost:8081"
                },
                "response_types_supported": {
                    "type": "array",
                    "items": {
                        "type": "string"
                    },
                    "example": [
                        "code"
                    ]
                },
                "scopes_supported": {
                    "type": "array",
                    "items": {
                        "type": "string"
                    },
                    "example": [
                        "library:read",
                        "library:write"
                    ]
                },
                "token_endpoint": {
                    "type": "string",
                    "example": "http://localhost:8081/oauth/token"
                },
                "token_endpoint_auth_methods_supported": {
                    "type": "array",
                    "items": {
                        "type": "string"
                    },
                    "example": [
                        "client_secret_basic"
                    ]
                }
            }
        },
        "response.User": {
            "type": "object",
            "properties": {
                "createdAt": {
                    "type": "string",
                    "example": "2026-07-19T08:00:00Z"
                },
                "email": {
                    "type": "string",
                    "example": "ada@example.com"
                },
                "id": {
                    "type": "string",
                    "example": "f81d4fae-7dec-11d0-a765-00a0c91e6bf6"
                },
                "name": {
                    "type": "string",
                    "example": "Ada Lovelace"
                },
                "updatedAt": {
                    "type": "string",
                    "example": "2026-07-19T08:00:00Z"
                }
            }
        },
        "response.UserSuccess": {
            "type": "object",
            "properties": {
                "code": {
                    "type": "string",
                    "example": "LMS-200000"
                },
                "data": {
                    "$ref": "#/definitions/response.User"
                }
            }
        }
    },
    "securityDefinitions": {
        "BasicAuth": {
            "type": "basic"
        },
        "BearerAuth": {
            "description": "Prefix access tokens with \"Bearer \".",
            "type": "apiKey",
            "name": "Authorization",
            "in": "header"
        }
    }
}